{
  "segments": [
    {
      "name": "大阪環状線",
      "stations": [
        {
          "id": "寺田町駅",
          "name": "1.0",
          "km": 1.0
        },
        {
          "id": "桃谷駅",
          "name": "1.2",
          "km": 2.2
        },
        {
          "id": "鶴橋駅",
          "name": "0.8",
          "km": 3.0
        },
        {
          "id": "玉造駅",
          "name": "0.9",
          "km": 3.9
        },
        {
          "id": "森ノ宮駅",
          "name": "0.9",
          "km": 4.8
        },
        {
          "id": "大阪城公園駅",
          "name": "0.9",
          "km": 5.7
        },
        {
          "id": "京橋駅",
          "name": "0.8",
          "km": 6.5
        },
        {
          "id": "桜ノ宮駅",
          "name": "1.8",
          "km": 8.3
        },
        {
          "id": "天満駅",
          "name": "0.8",
          "km": 9.1
        },
        {
          "id": "大阪駅",
          "name": "1.6",
          "km": 10.7
        },
        {
          "id": "福島駅",
          "name": "1.0",
          "km": 11.7
        },
        {
          "id": "野田駅",
          "name": "1.4",
          "km": 13.1
        },
        {
          "id": "西九条駅",
          "name": "1.2",
          "km": 14.3
        },
        {
          "id": "弁天町駅",
          "name": "1.6",
          "km": 15.9
        },
        {
          "id": "大正駅",
          "name": "1.8",
          "km": 17.7
        },
        {
          "id": "芦原橋駅",
          "name": "1.2",
          "km": 18.9
        },
        {
          "id": "今宮駅",
          "name": "0.6",
          "km": 19.5
        },
        {
          "id": "新今宮駅",
          "name": "1.2",
          "km": 20.7
        },
        {
          "id": "天王寺駅",
          "name": "1.0",
          "km": 21.7
        }
      ]
    },
    {
      "name": "呉線",
      "stations": [
        {
          "id": "須波駅",
          "name": "5.1",
          "km": 5.1
        },
        {
          "id": "安芸幸崎駅",
          "name": "6.7",
          "km": 11.8
        },
        {
          "id": "忠海駅",
          "name": "5.4",
          "km": 17.2
        },
        {
          "id": "安芸長浜駅",
          "name": "2.8",
          "km": 20.0
        },
        {
          "id": "大乗駅",
          "name": "1.8",
          "km": 21.8
        },
        {
          "id": "竹原駅",
          "name": "3.5",
          "km": 25.3
        },
        {
          "id": "吉名駅",
          "name": "4.7",
          "km": 30.0
        },
        {
          "id": "安芸津駅",
          "name": "4.7",
          "km": 34.7
        },
        {
          "id": "風早駅",
          "name": "3.2",
          "km": 37.9
        },
        {
          "id": "安浦駅",
          "name": "6.3",
          "km": 44.2
        },
        {
          "id": "安登駅",
          "name": "4.5",
          "km": 48.7
        },
        {
          "id": "安芸川尻駅",
          "name": "4.1",
          "km": 52.8
        },
        {
          "id": "仁方駅",
          "name": "4.8",
          "km": 57.6
        },
        {
          "id": "広駅",
          "name": "2.6",
          "km": 60.2
        },
        {
          "id": "新広駅",
          "name": "1.3",
          "km": 61.5
        },
        {
          "id": "安芸阿賀駅",
          "name": "1.4",
          "km": 62.9
        },
        {
          "id": "呉駅",
          "name": "4.1",
          "km": 67.0
        },
        {
          "id": "川原石駅",
          "name": "1.7",
          "km": 68.7
        },
        {
          "id": "吉浦駅",
          "name": "2.3",
          "km": 71.0
        },
        {
          "id": "かるが浜駅",
          "name": "1.2",
          "km": 72.2
        },
        {
          "id": "天応駅",
          "name": "2.1",
          "km": 74.3
        },
        {
          "id": "呉ポートピア駅",
          "name": "1.3",
          "km": 75.6
        },
        {
          "id": "小屋浦駅",
          "name": "1.5",
          "km": 77.1
        },
        {
          "id": "水尻駅",
          "name": "2.2",
          "km": 79.3
        },
        {
          "id": "坂駅",
          "name": "2.5",
          "km": 81.8
        },
        {
          "id": "矢野駅 広",
          "name": "2.6",
          "km": 84.4
        },
        {
          "id": "海田市駅 広",
          "name": "2.6",
          "km": 87.0
        },
        {
          "id": "向洋駅 広",
          "name": "2.3",
          "km": 89.3
        },
        {
          "id": "天神川駅 広",
          "name": "1.8",
          "km": 91.1
        },
        {
          "id": "広島駅 広",
          "name": "2.3",
          "km": 93.4
        }
      ]
    },
    {
      "name": "JR京都線",
      "stations": [
        {
          "id": "JR-A32",
          "name": "西大路京",
          "km": 0.7
        },
        {
          "id": "JR-A33",
          "name": "桂川京",
          "km": 2.8
        },
        {
          "id": "JR-A34",
          "name": "向日町",
          "km": 1.1
        },
        {
          "id": "JR-A35",
          "name": "長岡京",
          "km": 3.7
        },
        {
          "id": "JR-A36",
          "name": "山崎",
          "km": 4.0
        },
        {
          "id": "JR-A37",
          "name": "島本",
          "km": 2.2
        },
        {
          "id": "JR-A38",
          "name": "高槻",
          "km": 5.3
        },
        {
          "id": "JR-A39",
          "name": "摂津富田",
          "km": 2.9
        },
        {
          "id": "JR-A40",
          "name": "JR総持寺",
          "km": 1.7
        },
        {
          "id": "JR-A41",
          "name": "茨木",
          "km": 2.0
        },
        {
          "id": "JR-A42",
          "name": "千里丘",
          "km": 2.9
        },
        {
          "id": "JR-A43",
          "name": "岸辺",
          "km": 1.7
        },
        {
          "id": "JR-A44",
          "name": "吹田",
          "km": 1.5
        },
        {
          "id": "JR-A45",
          "name": "東淀川",
          "km": 3.1
        },
        {
          "id": "JR-A46",
          "name": "新大",
          "km": 0.7
        }
      ]
    }
  ]
}